README.rst
setup.py
./dorothy_sdk/__init__.py
./dorothy_sdk/core.py
./dorothy_sdk/dataset_wrapper.py
./dorothy_sdk/git_repo.py
./dorothy_sdk/mlflow.py
./dorothy_sdk/operation.py
./dorothy_sdk/session.py
./dorothy_sdk/utils.py
./dorothy_sdk/version.py
./dorothy_sdk.egg-info/PKG-INFO
./dorothy_sdk.egg-info/SOURCES.txt
./dorothy_sdk.egg-info/dependency_links.txt
./dorothy_sdk.egg-info/requires.txt
./dorothy_sdk.egg-info/top_level.txt
./dorothy_sdk/resources/__init__.py
./dorothy_sdk/resources/dataset.py
./dorothy_sdk/resources/folders.py
./dorothy_sdk/resources/folds.py
./dorothy_sdk/resources/image.py
./dorothy_sdk/resources/quality_annotation.py
bin/model_run
bin/model_train