Metadata-Version: 2.1
Name: dorothy-sdk
Version: 1.4.0
Summary: UNKNOWN
Home-page: https://github.com/tb-brics/dorothy-sdk
Author: Patrick Braz
Author-email: patrickfbraz@poli.ufrj.br
Maintainer: Patrick Braz
Maintainer-email: patrickfbraz@poli.ufrj.br
License: UNKNOWN
Platform: UNKNOWN
Classifier: Programming Language :: Python :: 3
Classifier: Operating System :: OS Independent
Requires-Python: >=3.6
